okahu_apptrace/__init__.py
okahu_apptrace/exporter.py
okahu_apptrace/instrumentor.py
okahu_apptrace/utils.py
okahu_apptrace/wrap_common.py
okahu_apptrace/wrapper.py
okahu_apptrace/haystack/README.md
okahu_apptrace/haystack/__init__.py
okahu_apptrace/haystack/wrap_node.py
okahu_apptrace/haystack/wrap_openai.py
okahu_apptrace/haystack/wrap_pipeline.py
okahu_apptrace/langchain/__init__.py
okahu_apptrace/llamaindex/__init__.py
okahu_observability-0.0.7.dist-info/METADATA
okahu_observability-0.0.7.dist-info/WHEEL
okahu_observability-0.0.7.dist-info/licenses/LICENSE
okahu_observability-0.0.7.dist-info/RECORD
