Metadata-Version: 2.3
Name: okahu-observability
Version: 0.0.7
Summary: package with okahu opentelemetry
Project-URL: Homepage, https://github.com/okahu/demo-repository
Project-URL: Issues, https://github.com/okahu/demo-repository/issues
Author-email: "Okahu Inc." <okahu-pypi@okahu.ai>
License-File: LICENSE
Classifier: License :: OSI Approved :: MIT License
Classifier: Operating System :: OS Independent
Classifier: Programming Language :: Python :: 3
Requires-Python: >=3.8
Requires-Dist: opentelemetry-api>=1.21.0
Requires-Dist: opentelemetry-instrumentation
Requires-Dist: opentelemetry-sdk>=1.21.0
Requires-Dist: requests
Requires-Dist: wrapt>=1.14.0
Provides-Extra: dev
Requires-Dist: faiss-cpu==1.7.4; extra == 'dev'
Requires-Dist: instructorembedding==1.0.1; extra == 'dev'
Requires-Dist: langchain-openai==0.0.5; extra == 'dev'
Requires-Dist: llama-index-embeddings-huggingface==0.2.0; extra == 'dev'
Requires-Dist: llama-index==0.10.30; extra == 'dev'
Requires-Dist: numpy==1.26.4; extra == 'dev'
Requires-Dist: pytest==8.0.0; extra == 'dev'
Requires-Dist: sentence-transformers==2.6.1; extra == 'dev'
Requires-Dist: types-requests==2.31.0.20240106; extra == 'dev'
